tinyweather/__init__.py
tinyweather/main.py
tinyweather/script.py
tinyweather/sensors.py
tinyweather-0.2.0.dist-info/LICENSE
tinyweather-0.2.0.dist-info/WHEEL
tinyweather-0.2.0.dist-info/METADATA
tinyweather-0.2.0.dist-info/RECORD
