Metadata-Version: 2.1
Name: tinyweather
Version: 0.2.0
Summary: Software for a home weather station
Author-email: Elyas Bianchi <elyasb99@gmail.com>
Classifier: License :: OSI Approved :: MIT License
Project-URL: Home, https://github.com/Elyasb14/tinyweather
